io_beep_boop/__init__.py
io_beep_boop/api/__init__.py
io_beep_boop/api/client.py
io_beep_boop/api/models.py
io_beep_boop/cli/__main__.py
io_beep_boop/tests/conftest.py
io_beep_boop/tests/test_something.py
io_beep_boop-0.1.1.dist-info/METADATA
io_beep_boop-0.1.1.dist-info/WHEEL
io_beep_boop-0.1.1.dist-info/entry_points.txt
io_beep_boop-0.1.1.dist-info/licenses/LICENSE.txt
io_beep_boop-0.1.1.dist-info/RECORD
